tbf/__init__.py
tbf/cli.py
tbf/tbf.py
tbf-0.2.0.dist-info/DESCRIPTION.rst
tbf-0.2.0.dist-info/METADATA
tbf-0.2.0.dist-info/RECORD
tbf-0.2.0.dist-info/WHEEL
tbf-0.2.0.dist-info/entry_points.txt
tbf-0.2.0.dist-info/metadata.json
tbf-0.2.0.dist-info/top_level.txt
