Metadata-Version: 2.0
Name: tbf
Version: 0.2.0
Summary: Typecraft Binary Format, a super-optimized IGT format
Home-page: https://github.com/Typecraft/tbf
Author: Tormod Haugland
Author-email: tormod.haugland@gmail.com
License: MIT license
Keywords: tbf
Platform: UNKNOWN
Classifier: Development Status :: 2 - Pre-Alpha
Classifier: Intended Audience :: Developers
Classifier: License :: OSI Approved :: MIT License
Classifier: Natural Language :: English
Classifier: Programming Language :: Python :: 3
Classifier: Programming Language :: Python :: 3.4
Classifier: Programming Language :: Python :: 3.6
Requires-Dist: Click (>=6.0)
